optimal1dclustering-1.0.2.dist-info/WHEEL
optimal1dclustering-1.0.2.dist-info/top_level.txt
optimal1dclustering-1.0.2.dist-info/RECORD
optimal1dclustering-1.0.2.dist-info/METADATA
optimal1dclustering-1.0.2.dist-info/LICENSE
optimal1dclustering/__init__.py
optimal1dclustering/version.txt
optimal1dclustering/_core.cpython-39-x86_64-linux-gnu.so
optimal1dclustering/core.py
