Metadata-Version: 2.1
Name: optimal1dclustering
Version: 1.0.2
Summary: A Python package for Optimal 1D Clustering
Home-page: 
Author: Jan Meißner, Daniel Steinberg
Author-email: philipp.meissner@rwth-aachen.de, ds@dannyadam.com
Maintainer: Jan Meißner
Maintainer-email: philipp.meissner@rwth-aachen.de
License: MIT
Keywords: k-means,k-median,machine learning,optimization
Classifier: Development Status :: 4 - Beta
Classifier: Intended Audience :: Developers
Classifier: Intended Audience :: Science/Research
Classifier: Topic :: Scientific/Engineering
Classifier: Topic :: Scientific/Engineering :: Artificial Intelligence
Classifier: Topic :: Scientific/Engineering :: Information Analysis
Classifier: License :: OSI Approved :: MIT License
Classifier: Operating System :: Unix
Classifier: Operating System :: POSIX :: Linux
Classifier: Operating System :: MacOS
Classifier: Operating System :: Microsoft :: Windows
Classifier: Programming Language :: Python :: 3
Requires-Python: >=3.6
License-File: LICENSE
